serif/__init__.py
serif/alias_tracker.py
serif/csv.py
serif/display.py
serif/errors.py
serif/naming.py
serif/table.py
serif/typeutils.py
serif/typing.py
serif/vector.py
serif-0.1.1.dist-info/licenses/LICENSE
serif-0.1.1.dist-info/METADATA
serif-0.1.1.dist-info/WHEEL
serif-0.1.1.dist-info/top_level.txt
serif-0.1.1.dist-info/RECORD
