Metadata-Version: 2.4
Name: serif
Version: 0.1.1
Summary: A Pythonic, zero-dependency vector and table library for interactive data exploration
Author-email: Ryan Larsen <ryan.e.larsen@gmail.com>
License: MIT License
Project-URL: Homepage, https://github.com/CIG-GitHub/serif
Project-URL: Repository, https://github.com/CIG-GitHub/serif
Project-URL: Bug Tracker, https://github.com/CIG-GitHub/serif/issues
Keywords: vector,table,data,analysis,dataframe,csv
Classifier: Development Status :: 3 - Alpha
Classifier: Intended Audience :: Developers
Classifier: Intended Audience :: Science/Research
Classifier: License :: OSI Approved :: MIT License
Classifier: Programming Language :: Python :: 3
Classifier: Programming Language :: Python :: 3.10
Classifier: Programming Language :: Python :: 3.11
Classifier: Programming Language :: Python :: 3.12
Classifier: Programming Language :: Python :: 3.13
Classifier: Topic :: Software Development :: Libraries :: Python Modules
Classifier: Topic :: Scientific/Engineering
Requires-Python: >=3.10
License-File: LICENSE
Provides-Extra: dev
Requires-Dist: pytest>=7.0; extra == "dev"
Dynamic: license-file
